.source test/test_if.selma
.class public Main
.super java/lang/Object
.field public static scanner_field Ljava/util/Scanner;
.field public static i_1 I 
.field public static b_1 C 
.method public <init>()V
    aload_0
    invokespecial java/lang/Object/<init>()V
    return
.end method
.method public static main([Ljava/lang/String;)V
.limit stack 7
.limit locals 4
    new java/util/Scanner
    dup                                       ; dup for <init>
    getstatic java/lang/System/in Ljava/io/InputStream;
    invokespecial java/util/Scanner/<init>(Ljava/io/InputStream;)V
    putstatic Main/scanner_field Ljava/util/Scanner;
.line 1
.line 3
    iconst_0
                            ; e1 right hand for assignment
    dup
    putstatic Main/i_1 I
    pop
.line 5
    iconst_1
                            ; e1 right hand for assignment
    dup
    putstatic Main/i_1 I
    iconst_1
    if_icmpeq L0        ; e1 = e2
    iconst_0
    goto L1
L0:
    iconst_1
L1:
    ifeq L2          ; e1 is false
.line 6
.line 8
    bipush 20
                            ; e1 right hand for assignment
    dup
    putstatic Main/i_1 I
    pop
.line 10
    getstatic Main/i_1 I ; load global i_1
    dup
    getstatic java/lang/System/out Ljava/io/PrintStream;
    swap
    invokevirtual java/io/PrintStream/println(I)V
    pop
    goto L3
L2:
.line 12
    bipush 104                ; ldc 'h'
    getstatic java/lang/System/out Ljava/io/PrintStream;
    swap
    invokevirtual java/io/PrintStream/println(C)V
 .line 12
    bipush 101                ; ldc 'e'
    getstatic java/lang/System/out Ljava/io/PrintStream;
    swap
    invokevirtual java/io/PrintStream/println(C)V
 .line 12
    bipush 108                ; ldc 'l'
    getstatic java/lang/System/out Ljava/io/PrintStream;
    swap
    invokevirtual java/io/PrintStream/println(C)V
 .line 12
    bipush 108                ; ldc 'l'
    getstatic java/lang/System/out Ljava/io/PrintStream;
    swap
    invokevirtual java/io/PrintStream/println(C)V
 .line 12
    bipush 111                ; ldc 'o'
    getstatic java/lang/System/out Ljava/io/PrintStream;
    swap
    invokevirtual java/io/PrintStream/println(C)V
							; e3 if false expression
L3:
.line 18
.line 19
    ldc 1                   ; load constant b_1
    ifeq L4          ; e1 is false
.line 20
.line 21
    bipush 98                ; ldc 'b'                            ; e1 right hand for assignment
    dup
    putstatic Main/b_1 C
    pop
.line 24
    getstatic Main/b_1 C ; load global b_1
    dup
    getstatic java/lang/System/out Ljava/io/PrintStream;
    swap
    invokevirtual java/io/PrintStream/println(C)V
    goto L5
L4:
.line 26
    bipush 99                ; ldc 'c'
L5:
    dup
    getstatic java/lang/System/out Ljava/io/PrintStream;
    swap
    invokevirtual java/io/PrintStream/println(C)V
    pop
.line 29
    iconst_1
    iconst_1
    if_icmpne L6        ; e1 != e2
    iconst_0
    goto L7
L6:
    iconst_1
L7:
    ifeq L8          ; e1 is false
.line 30
    bipush 97                ; ldc 'a'
    getstatic java/lang/System/out Ljava/io/PrintStream;
    swap
    invokevirtual java/io/PrintStream/println(C)V
 .line 30
    bipush 98                ; ldc 'b'
    getstatic java/lang/System/out Ljava/io/PrintStream;
    swap
    invokevirtual java/io/PrintStream/println(C)V
                           ; e2 if true expression
L8:
    return
.end method
