.source test/test_functions/correct_functions.SELMA
.class public Main
.super java/lang/Object
.field public static scanner_field Ljava/util/Scanner;
.field public static v_1 I 
.method public <init>()V
    aload_0
    invokespecial java/lang/Object/<init>()V
    return
.end method
.method public static main([Ljava/lang/String;)V
.limit stack 6
.limit locals 7
    new java/util/Scanner
    dup                                       ; dup for <init>
    getstatic java/lang/System/in Ljava/io/InputStream;
    invokespecial java/util/Scanner/<init>(Ljava/io/InputStream;)V
    putstatic Main/scanner_field Ljava/util/Scanner;
.line 13
.line 38
    invokestatic Main/foo()V
.line 39
    iconst_1
    iconst_2
    iconst_0
    invokestatic Main/foo1(III)V
.line 40
    ldc 99                   ; load constant c_1
    dup
    getstatic java/lang/System/out Ljava/io/PrintStream;
    swap
    invokevirtual java/io/PrintStream/println(C)V
    pop
.line 41
    invokestatic Main/foo2()I
    dup
    getstatic java/lang/System/out Ljava/io/PrintStream;
    swap
    invokevirtual java/io/PrintStream/println(I)V
    pop
.line 42
    iconst_1
    iconst_2
    iconst_1
    invokestatic Main/foo3(III)I
    dup
    getstatic java/lang/System/out Ljava/io/PrintStream;
    swap
    invokevirtual java/io/PrintStream/println(I)V
    pop
    return
.end method
.method public static foo()V
.limit stack 4
.limit locals 1
.line 16
.line 17
    bipush 25
                            ; e1 right hand for assignment
    dup
    putstatic Main/v_1 I
    pop
    return
.end method
.method public static foo1(III)V
.limit stack 4
.limit locals 4
.line 20
.line 21
    iconst_1
    pop
    return
.end method
.method public static foo2()I
.limit stack 5
.limit locals 1
.line 24
.line 25
    getstatic Main/v_1 I ; load global v_1
    getstatic java/lang/System/out Ljava/io/PrintStream;
    swap
    invokevirtual java/io/PrintStream/println(I)V
     ldc 99                   ; load constant c_1
    getstatic java/lang/System/out Ljava/io/PrintStream;
    swap
    invokevirtual java/io/PrintStream/println(C)V
    bipush 6
    ireturn
.end method
.method public static foo3(III)I
.limit stack 7
.limit locals 5
.line 29
.line 30
.line 32
    iconst_3
                            ; e1 right hand for assignment
    dup
    istore 3               ; store e1 in v_1
    pop
.line 33
    iload 0                ; load a_1 from 0
    getstatic java/lang/System/out Ljava/io/PrintStream;
    swap
    invokevirtual java/io/PrintStream/println(I)V
     iload 1                ; load b_1 from 1
    getstatic java/lang/System/out Ljava/io/PrintStream;
    swap
    invokevirtual java/io/PrintStream/println(I)V
     iload 2                ; load c_1 from 2
    ifeq L0
    ldc "true"
    goto L1
L0:
    ldc "false"
L1:
    getstatic java/lang/System/out Ljava/io/PrintStream;
    swap
    invokevirtual java/io/PrintStream/println(Ljava/lang/String;)V
     iload 3                ; load v_1 from 3
    getstatic java/lang/System/out Ljava/io/PrintStream;
    swap
    invokevirtual java/io/PrintStream/println(I)V
.line 34
    iload 0                ; load a_1 from 0
    iload 1                ; load b_1 from 1
    imul
    iconst_5
    iadd
    ireturn
.end method
